litebem/__init__.py
litebem/postprocessing/__init__.py
litebem/postprocessing/results.py
litebem/preprocessing/__init__.py
litebem/preprocessing/airy_waves.py
litebem/preprocessing/bem_problem_definitions.py
litebem/preprocessing/body.py
litebem/preprocessing/mesh.py
litebem/solver/__init__.py
litebem/solver/bem_solver.py
litebem/solver/linear_solvers.py
litebem/solver/green_functions/__init__.py
litebem/solver/green_functions/abstract_green_function.py
litebem/solver/green_functions/delhommeau.py
litebem/solver/green_functions/delhommeau_f90.cp39-win_amd64.pyd
litebem-1.0.2.dist-info/LICENSE
litebem-1.0.2.dist-info/METADATA
litebem-1.0.2.dist-info/WHEEL
litebem-1.0.2.dist-info/top_level.txt
litebem-1.0.2.dist-info/RECORD
