Metadata-Version: 2.1
Name: litebem
Version: 1.0.2
Summary: A lightweight, Apache 2.0 distribution of Matthieu Ancellin`s Capytaine BEM code.
Home-page: https://github.com/dav-og/liteBEM
Author: mancellin, dav-og, dunc-lamb
License: Apache-2.0
Classifier: Programming Language :: Python
Classifier: License :: OSI Approved :: Apache Software License
Classifier: Operating System :: OS Independent
Classifier: Topic :: Scientific/Engineering
Requires-Python: >=3.0
License-File: LICENSE
Requires-Dist: pytest
Requires-Dist: numpy
Requires-Dist: scipy
Requires-Dist: pandas
Requires-Dist: xarray
